{
  "courseTitle": "大學統計學",
  "version": "1.0",
  "chapters": [
    {
      "chapterNumber": "16",
      "chapterTitle": "非參數統計方法",
      "overview": "本章介紹非參數統計方法的核心概念與應用，幫助學生掌握統計學的基礎知識並應用於實際問題分析。",
      "sections": [
        {
          "sectionNumber": "16.1",
          "sectionTitle": "非參數統計的概念與應用場景",
          "content": "非參數統計方法是指在研究樣本資料的分布、參數和假設時，不對母體分布進行任何特定形式的假設。換句話說，非參數統計方法不依賴於母體的具體分布形式，因此在某些情況下更加靈活和實用。這些方法通常基於觀察到的數據進行推斷，而非依賴於母體分布的具體形式。\n\n非參數統計方法在樣本數較小、缺乏常態性假設或者母體分布難以確定時特別有用。它們通常以排序、計數或者比較順序來進行統計推斷，如秩和檢定、符號檢定和卡方檢定等。",
          "examples": [
            "假設我們想要比較兩個治療方法對於某種疾病的療效。如果我們無法確定患者數據的分佈情況，可以使用Wilcoxon符號秩檢定來進行比較，這是一種非參數統計方法。",
            "在市場調查中，若要比較兩種廣告對於產品銷量的影響，但無法確定銷量數據的分布是否符合常態分佈，可以使用Mann-Whitney U檢定來進行比較。",
            "在生態學研究中，我們可能需要比較不同環境條件對於物種多樣性的影響，此時可以使用Kruskal-Wallis檢定來進行統計分析。"
          ],
          "visuals": [
            {
              "path": "/static/images/ch16/16_1.png",
              "description": "非參數統計的概念與應用場景的圖解"
            }
          ],
          "mnemonics": [
            "非參數統計方法的「非參數」意味著不需要知道母體的具體參數，只需要觀察樣本數據。",
            "非參數統計方法通常基於數據的排序或比較順序，有助於彌補常態性假設無法滿足的情況。"
          ],
          "exercises": [
            {
              "type": "short_answer",
              "question": "請解釋非參數統計方法的概念及其適用場景。",
              "answer": "非參數統計方法是指在不對母體分佈做出特定假設的情況下進行統計推斷的方法。它適用於樣本數較小、不滿足常態性假設或者母體分布未知的情況。"
            },
            {
              "type": "short_answer",
              "question": "請舉例說明一個使用非參數統計方法的實際應用場景。",
              "answer": "一個使用非參數統計方法的例子是比較兩種不同教學方法對學生成績的影響，但無法確定成績分佈是否符合常態分佈時，可以使用秩和檢定進行比較。"
            },
            {
              "type": "short_answer",
              "question": "什麼是Wilcoxon符號秩檢定，它在什麼情況下適用？",
              "answer": "Wilcoxon符號秩檢定是一種非參數統計方法，用於比較兩組配對樣本的差異。當數據無法確認為常態分佈時，可以使用這種方法來檢定兩組樣本的差異。"
            }
          ]
        },
        {
          "sectionNumber": "16.2",
          "sectionTitle": "符號檢定",
          "content": "符號檢定是一種非參數統計方法，用於檢驗兩個母體的中位數是否相等。這種方法適用於對數據的分佈形狀沒有具體假設的情況，通常用於小樣本或資料非常偏斜的情況下。在符號檢定中，我們將觀察到的數據轉換為符號，例如大於某個值、小於某個值或等於某個值，然後計算符號的數量來進行假設檢定。\n\n假設我們有兩組數據，我們想檢驗它們的中位數是否相等。我們首先將兩組數據合併並將數據按照大小排序。然後對於每對數據，我們檢查它們的大小關係，如果一組數據的數值比另一組數據大，我們就記為\"+\"；如果小，就記為\"-\"；如果相等，就記為\"=\"。最後，我們統計\"+\"和\"-\"的個數，利用這個統計量來進行假設檢定。",
          "examples": [
            "一家公司想要比較兩個不同訓練方法對員工工作表現的影響。他們收集了兩組員工的績效數據，並使用符號檢定來檢驗兩個訓練方法是否存在差異。",
            "一個研究人員想要研究兩種不同治療方法對病人癒合時間的影響。通過符號檢定，他們可以確定兩種治療方法是否在癒合時間上有統計學差異。",
            "一個教育家想要測試兩種不同教學法對學生學習成績的影響。通過符號檢定，他可以比較兩種教學法是否對學生成績有顯著不同。"
          ],
          "visuals": [
            {
              "path": "/static/images/ch16/16_2.png",
              "description": "符號檢定的圖解"
            }
          ],
          "mnemonics": [
            "將符號檢定比喻為一種簡單的「大小比較遊戲」，有助於記憶符號的轉換方式。",
            "記住符號檢定主要用於中位數的比較，可以通過「中位數比大小」來聯想。"
          ],
          "exercises": [
            {
              "type": "short_answer",
              "question": "小明想比較兩種不同學習方法對他的成績是否有影響。他對兩種方法進行了測試，結果如下：方法A共有8次測試，他在7次中取得了較好成績；方法B共有10次測試，他在6次中取得了較好成績。請根據這些結果使用符號檢定來檢驗兩種學習方法是否存在差異。",
              "answer": "將方法A的成績記為\"+\"，方法B的成績記為\"-\"，則共有7個\"+\"和3個\"-\"，按照符號檢定的方法，我們可以計算出p值，判斷是否存在統計學差異。"
            },
            {
              "type": "short_answer",
              "question": "一個營銷部門想要比較兩個不同促銷策略對產品銷量的影響。他們隨機選擇了兩組分店，一組實施策略A，另一組實施策略B。在一個月的實驗後，結果顯示策略A的平均銷量高於策略B。請使用符號檢定來檢驗這兩種促銷策略是否存在顯著差異。",
              "answer": "將策略A的銷量記為\"+\"，策略B的銷量記為\"-\"，根據符號檢定的方法計算結果，判斷兩種促銷策略是否具有統計學差異。"
            },
            {
              "type": "short_answer",
              "question": "一個健身教練想要比較兩種不同訓練計畫對客戶體重減輕效果的影響。他收集了兩組客戶的體重減輕數據，請使用符號檢定來驗證兩個訓練計畫是否有統計學差異。",
              "answer": "將第一組客戶的減重記為\"+\"，第二組客戶的減重記為\"-\"，根據符號檢定的方法進行統計檢定，得出結果。"
            }
          ]
        },
        {
          "sectionNumber": "16.3",
          "sectionTitle": "Wilcoxon符號等級檢定",
          "content": "Wilcoxon符號等級檢定是一個非參數統計方法，用於比較兩組配對樣本之間的差異。這個檢定方法將兩組配對樣本的差異轉換為一組差異的等級，然後根據這些等級來進行統計檢定。與t檢定相比，Wilcoxon符號等級檢定更適用於處理資料不服從正態分佈或有極端值的情況。\n\nWilcoxon符號等級檢定的步驟包括：首先計算每對配對樣本的差異；然後將這些差異的絕對值進行排序，並賦予等級；接著計算正差異等級的總和，以及負差異等級的總和；最後，根據總和的大小來進行統計檢定。這個方法的原假設是兩組配對樣本的差異沒有顯著差異，而對立假設是兩組配對樣本的差異有顯著差異。",
          "examples": [
            "一個研究想要比較一組學生在數學考試前後的成績差異。研究者使用Wilcoxon符號等級檢定來確定學生的成績是否有顯著的提升或下降。",
            "一個醫學研究中，醫生想要評估一種新藥物對患者血壓的影響。研究者使用Wilcoxon符號等級檢定來比較患者服用藥物前後的血壓數據。",
            "一個心理學研究中，研究者想要研究一種新的治療方法對患者焦慮水平的影響。研究者使用Wilcoxon符號等級檢定來比較患者接受治療前後的焦慮水平。"
          ],
          "visuals": [
            {
              "path": "/static/images/ch16/16_3.png",
              "description": "Wilcoxon符號等級檢定的圖解"
            }
          ],
          "mnemonics": [
            "記住Wilcoxon符號等級檢定的步驟：計算差異、排序並賦予等級、計算正、負差異等級總和、進行統計檢定。",
            "將Wilcoxon符號等級檢定想像成將配對樣本的差異轉換成一種等級，然後根據這些等級來進行比較，有助於理解其原理和應用。"
          ],
          "exercises": [
            {
              "type": "short_answer",
              "question": "一個研究想要比較一組受訓前後的員工在工作表現上的差異。請使用Wilcoxon符號等級檢定來進行統計檢定。",
              "answer": "計算差異、排序並賦予等級、計算正、負差異等級總和，進行統計檢定。"
            },
            {
              "type": "short_answer",
              "question": "一個實驗想要評估兩種不同肥料對植物生長的影響。請使用Wilcoxon符號等級檢定來比較兩種肥料對植物生長的效果。",
              "answer": "計算差異、排序並賦予等級、計算正、負差異等級總和，進行統計檢定。"
            },
            {
              "type": "short_answer",
              "question": "一個研究想要瞭解一個新教學方法對學生學習成效的影響。請使用Wilcoxon符號等級檢定來評估新教學方法的效果。",
              "answer": "計算差異、排序並賦予等級、計算正、負差異等級總和，進行統計檢定。"
            }
          ]
        },
        {
          "sectionNumber": "16.4",
          "sectionTitle": "Mann-Whitney U檢定",
          "content": "Mann-Whitney U檢定，又稱為Mann-Whitney-Wilcoxon檢定，是一種非參數統計方法，用於比較兩組獨立樣本的中位數是否相等。這個檢定方法適用於兩組樣本的母體不滿足正態分佈的情況下。Mann-Whitney U檢定基於將兩組資料合併後，依據大小順序賦予排名，然後計算排名和。透過比較排名和來判斷兩組樣本的中位數是否有顯著差異。",
          "examples": [
            "假設要比較兩組學生在數學考試成績上的中位數是否有顯著差異，可以使用Mann-Whitney U檢定。",
            "在醫療研究中，可以利用Mann-Whitney U檢定比較兩種不同治療方法對患者症狀改善的效果。",
            "在市場調查中，可以使用Mann-Whitney U檢定來比較兩個產品在消費者評分上的中位數是否有統計顯著差異。"
          ],
          "visuals": [
            {
              "path": "/static/images/ch16/16_4.png",
              "description": "Mann-Whitney U檢定的圖解"
            }
          ],
          "mnemonics": [
            "記住Mann-Whitney U檢定是用來比較兩組獨立樣本的中位數，而且是非參數統計方法。",
            "想像將兩組資料混合在一起，然後根據大小排名，再計算排名和來進行比較。"
          ],
          "exercises": [
            {
              "type": "short_answer",
              "question": "一個研究想比較兩種不同營養補充劑對運動員體能表現的影響，樣本數分別為20和25。請使用Mann-Whitney U檢定來判斷這兩種補充劑是否有顯著差異。",
              "answer": "計算兩組資料的排名和，並進行統計檢定，得出結論。"
            },
            {
              "type": "short_answer",
              "question": "一間公司想比較兩組員工的平均工作時數是否有顯著差異，樣本數分別為30和35。應該使用哪種統計方法？",
              "answer": "由於是比較中位數而非平均值，因此應使用Mann-Whitney U檢定。"
            },
            {
              "type": "short_answer",
              "question": "一個研究想探討兩組受訓者在測驗成績上的差異，樣本大小分別為15和18。請進行Mann-Whitney U檢定。",
              "answer": "將兩組資料合併，計算排名和並進行檢定，得出結論。"
            }
          ]
        },
        {
          "sectionNumber": "16.5",
          "sectionTitle": "Kruskal-Wallis檢定",
          "content": "Kruskal-Wallis檢定是一種非參數統計方法，用於檢驗三個或三個以上獨立樣本的中位數是否相等。當資料不符合常態分佈或無法滿足方差齊性的假設時，Kruskal-Wallis檢定是一個有效的替代方法。這個檢定基於排序後的數據，將各組的數據合併後重新排序，然後計算每個數據對應的順位，最後根據順位來進行統計檢定。\n\n在執行Kruskal-Wallis檢定時，我們假設原假設為各組樣本來自相同的總體，對立假設為至少有一組樣本來自不同的總體。透過計算組內排名總和、計算組間排名總和、以及計算檢定統計量，我們可以得出統計結果，進而判斷是否拒絕原假設。",
          "examples": [
            "一個研究人員想研究不同種類肥料對植物生長速度的影響。他將植物分為三組，分別施用三種不同的肥料，並測量生長速度。透過Kruskal-Wallis檢定，可以確定這三種肥料對植物生長速度是否有顯著影響。",
            "一家公司想比較不同訓練方法對員工表現的影響。他們將員工分為四組，進行不同的訓練，然後測試其表現。透過Kruskal-Wallis檢定，可以判斷這些訓練方法是否對員工表現有顯著差異。",
            "一個醫學研究小組希望研究不同治療方法對病人疼痛程度的影響。他們將病人分為五組，接受不同的治療，然後記錄疼痛程度。透過Kruskal-Wallis檢定，可以確定這些治療方法是否對疼痛程度產生顯著影響。"
          ],
          "visuals": [
            {
              "path": "/static/images/ch16/16_5.png",
              "description": "Kruskal-Wallis檢定的圖解"
            }
          ],
          "mnemonics": [
            "記住Kruskal-Wallis檢定用於三個或三個以上獨立樣本的中位數比較。",
            "想像將數據進行重新排序，根據順位來判斷差異。"
          ],
          "exercises": [
            {
              "type": "short_answer",
              "question": "一個研究人員想比較不同品牌汽車的耐久度。他將三個品牌的汽車分別進行測試，得到以下結果：品牌A：[210, 220, 230, 240, 250]；品牌B：[200, 195, 210, 220, 215]；品牌C：[225, 230, 240, 235, 220]。請使用Kruskal-Wallis檢定來判斷這三個品牌汽車的耐久度是否有顯著差異。",
              "answer": "首先將所有數據合併排序得到：[195, 200, 210, 210, 215, 220, 220, 225, 230, 230, 235, 240, 240, 250]。計算各組排名總和，然後根據檢定統計量進行統計檢定，最後得出結論。"
            },
            {
              "type": "short_answer",
              "question": "一個研究人員想比較不同種類水果的糖分含量。他將三種水果分別進行測試，得到以下結果：蘋果：[10, 12, 11, 13, 10]；橙子：[9, 11, 10, 12, 11]；香蕉：[8, 9, 10, 8, 11]。請使用Kruskal-Wallis檢定來判斷這三種水果的糖分含量是否有顯著差異。",
              "answer": "首先將所有數據合併排序得到：[8, 8, 9, 9, 10, 10, 10, 10, 11, 11, 11, 12, 12, 13]。計算各組排名總和，然後根據檢定統計量進行統計檢定，最後得出結論。"
            },
            {
              "type": "short_answer",
              "question": "一個研究人員想比較不同品牌電視的畫質表現。他將三個品牌的電視分別進行測試，得到以下結果：品牌X：[85, 88, 90, 87, 86]；品牌Y：[82, 85, 80, 84, 83]；品牌Z：[88, 89, 87, 90, 86]。請使用Kruskal-Wallis檢定來判斷這三個品牌電視的畫質表現是否有顯著差異。",
              "answer": "首先將所有數據合併排序得到：[80, 82, 83, 84, 85, 85, 86, 86, 87, 87, 88, 88, 89, 90, 90]。計算各組排名總和，然後根據檢定統計量進行統計檢定，最後得出結論。"
            }
          ]
        },
        {
          "sectionNumber": "16.6",
          "sectionTitle": "等級相關分析",
          "content": "等級相關分析是一種非參數統計方法，用於評估兩個變數之間的關係，但不要求這些變數是連續型的。這種方法通常用於處理順序資料，例如滿意度調查中的評分、教育水平等。等級相關分析的一個常見指標是Spearman等級相關係數，它衡量了兩個變數之間的單調關係。Spearman等級相關係數的值介於-1和1之間，接近1表示兩個變數呈正向關係，接近-1表示負向關係，接近0表示沒有線性相關性。",
          "examples": [
            "一家公司想研究員工的工作表現與他們在公司內部培訓考核的排名之間是否存在關係，可以使用Spearman等級相關分析來評估這兩者之間的相關性。",
            "在一項醫學研究中，研究人員想了解患者疾病嚴重程度與接受治療後康復狀況的關聯性，可以使用等級相關分析來評估這兩個變數之間的相關性。",
            "學生在學業成績和應對考試壓力的表現之間可能存在關係，可以利用等級相關分析來檢驗這種關係。"
          ],
          "visuals": [
            {
              "path": "/static/images/ch16/16_6.png",
              "description": "等級相關分析的圖解"
            }
          ],
          "mnemonics": [
            "記住Spearman等級相關係數的範圍是-1到1，接近1表示正向關係，接近-1表示負向關係。",
            "想像在一個等級相關分析中，你要按照不同的等級來排列變數，以觀察它們之間的關係。"
          ],
          "exercises": [
            {
              "type": "short_answer",
              "question": "一個研究人員想了解兩種新藥對患者疼痛程度的影響，他收集了患者使用藥物後的疼痛評分（1代表疼痛較輕，5代表疼痛較重）和使用藥物前後的排名。請用Spearman等級相關係數來評估這兩個變數之間的關係。",
              "answer": "利用Spearman等級相關分析計算這兩個變數的相關係數。"
            },
            {
              "type": "short_answer",
              "question": "一項研究調查了學生在一學期內的學習壓力水平和他們的學業表現之間的關係。研究人員收集了學生對學習壓力的評分（1代表輕度壓力，5代表極重壓力）和學期結束時的平均成績。請用等級相關分析來評估這兩個變數之間的關係。",
              "answer": "利用等級相關分析計算這兩個變數的相關係數。"
            },
            {
              "type": "short_answer",
              "question": "一個研究小組調查了不同社會階層人群對政府政策的支持程度與他們的收入水平之間的關係。他們收集了受訪者對政策的滿意度評分（1代表不滿意，5代表非常滿意）和他們的年收入。請用等級相關分析來評估這兩個變數之間的關係。",
              "answer": "利用等級相關分析計算這兩個變數的相關係數。"
            }
          ]
        },
        {
          "sectionNumber": "16.7",
          "sectionTitle": "使用統計軟體進行非參數檢定",
          "content": "在統計學中，非參數統計方法是一種不依賴於母體分佈假設的統計技術。當資料不符合常態分佈或無法確定母體分佈時，非參數方法就顯得特別重要。進行非參數檢定時，統計軟體的使用可以極大地簡化過程，提高效率。統計軟體可以計算出檢定統計量的值，並且幫助我們判斷是否拒絕虛無假設。常見的非參數檢定包括符號檢定、Wilcoxon符號秩檢定、Kruskal-Wallis檢定等，這些方法都可以在統計軟體中找到對應的工具。",
          "examples": [
            "一個研究人員想要比較兩組不同醫療治療對於病人生存率的影響，但是無法確定生存時間的分佈情況。這時可以使用統計軟體中的Wilcoxon符號秩檢定來比較兩組的生存時間中位數是否有顯著差異。",
            "一家公司想要了解員工對於新福利政策的滿意度是否存在差異，但是滿意度並不是一個連續變數。這時可以使用統計軟體中的Kruskal-Wallis檢定來比較不同福利政策下的員工滿意度是否有統計上的差異。",
            "一個研究團隊想要瞭解在不同天氣條件下人們的戶外活動時間是否存在差異，但是無法確定資料的分佈情況。這時可以使用統計軟體中的符號檢定來判斷在不同天氣條件下人們的戶外活動時間是否有差異。"
          ],
          "visuals": [
            {
              "path": "/static/images/ch16/16_7.png",
              "description": "使用統計軟體進行非參數檢定的圖解"
            }
          ],
          "mnemonics": [
            "**瞭解各種非參數檢定的特點和適用情況**：記住每種非參數檢定的使用條件和假設，可以幫助你在使用統計軟體時更快速地選擇適當的檢定方法。",
            "**熟練掌握統計軟體操作步驟**：熟練操作統計軟體中的非參數檢定工具，能夠幫助你更準確地進行檢定分析，提高工作效率。"
          ],
          "exercises": [
            {
              "type": "short_answer",
              "question": "請用統計軟體進行符號檢定，檢定一組資料是否符合某個理論中的中位數值為10的假設，數據如下：12, 8, 9, 11, 7, 10, 13。",
              "answer": "進行符號檢定後，計算出檢定統計量的值，並根據臨界值判斷是否拒絕虛無假設。"
            },
            {
              "type": "short_answer",
              "question": "使用統計軟體進行Kruskal-Wallis檢定，比較三組資料是否來自同一個母體，數據如下：\n組1：15, 18, 20, 22, 25\n組2：12, 14, 16, 19, 21\n組3：10, 13, 17, 23, 24",
              "answer": "進行Kruskal-Wallis檢定後，根據統計軟體輸出的結果判斷各組資料是否存在統計上的差異。"
            },
            {
              "type": "short_answer",
              "question": "利用統計軟體進行Wilcoxon符號秩檢定，比較兩組資料是否存在顯著差異，數據如下：\n組A：6, 8, 9, 12, 10\n組B：5, 7, 10, 11, 15",
              "answer": "進行Wilcoxon符號秩檢定後，根據統計軟體輸出的結果判斷兩組資料是否存在顯著差異。"
            }
          ]
        }
      ]
    }
  ]
}